{
  "byCitePatterns": {
    "CMR.ML": [
      "Common Metadata Ratings"
    ],
    "IANA.MT": [
      "iana media types",
      "/^media types$/i"
    ],
    "IANA": [
      "IANA"
    ],
    "IANA.LSR": [
      "Language Subtag Registry"
    ],
    "IETF.JSON.draft-bhutton-json-schema-00.2020": [
      "IETF draft-bhutton-json-schema-00",
      "/[\"“”']?JSON\\s+Schema:\\s+A\\s+Media\\s+Type\\s+for\\s+Describing\\s+JSON\\s+Documents[\"“”']?[\\s\\.]?$/i",
      "/\\bdraft-bhutton-json-schema-00\\b/i"
    ],
    "IETF.FLS.2001": [
      "Guidelines for the Use of Formal Languages in IETF Specifications"
    ],
    "ISBN.0195392884": [
      "/\\bNew Oxford American Dictionary, Third Edition\\b/i"
    ],
    "ISBN.9780205309023": [
      "/\\bElements of Style, Fourth Edition\\b/i"
    ],
    "ISDCF.DCNC": [
      "Digital Cinema Naming"
    ],
    "ISO.ICS": [
      "/\\bInternational Classification for Standards\\b/i"
    ],
    "ISO.Dir-P2.2011": [
      "iso/iec directives, part 2",
      "/^iso\\/iec directives part 2$/i"
    ],
    "LOC.DWG": [
      "DWG (AutoCAD Drawing) Format Family"
    ],
    "LOC.VSDX": [
      "Visio VSDX Drawing File Format"
    ],
    "OMG.XMI": [
      "XML Metadata Interchange (XMI)"
    ],
    "SMPTE.OM.BL": [
      "SMPTE Bylaws"
    ],
    "SMPTE.OM.Std": [
      "/^(?:SMPTE\\s+)?Standards Operation(s)? Manual$/i"
    ],
    "SMPTE.OM.Mem": [
      "/^SMPTE Membership Operation(s)? Manual$/i"
    ],
    "SMPTE.AG31": [
      "SMPTE GitHub Operating Manual",
      "SMPTE GitHub Operating Guidelines"
    ],
    "UN.SCAC.R4": [
      "Standard Country or Area Codes for Statistics Use, 1999 (Revision 4)"
    ],
    "WHATWG.HTML": [
      "HTML Standard",
      "/^the html standard$/i",
      "html living standard"
    ],
    "W3C.WSDL.1.1": [
      "W3C Web Services Description Language (WSDL) 1.1"
    ],
    "W3C.REC-html52.20171214": [
      "HTML 5.2",
      "/^html\\s*5\\.2$/i",
      "/\\bhtml\\s*5\\.2\\b/i"
    ]
  }
}